Workbook

Sheet Inputs
A1: tomphan. Should you buy an H100 today to rent it out? (one GPU)
A2: Blue = input. Green = linked from another sheet. Black = formula. Yellow = scenario selector. USD per GPU unless noted.
A4: Active scenario | B4: Base | C4: =MATCH(B4,{"Bull","Base","Bear"},0) -> 2
A6: Assumption | B6: Active | C6: Bull | D6: Base | E6: Bear | F6: Unit | G6: Source / why
A7: Capex per GPU, all-in | B7: =INDEX(C7:E7,$C$4) -> 35000 | C7: =D7 -> 35000 | D7: 35000 | E7: =D7 -> 35000 | F7: USD | G7: All-in cost per GPU incl. server share, network and storage. No open price series; tested from $20k to $40k.
A8: Rent, year 1 | B8: =INDEX(C8:E8,$C$4) -> 2.35 | C8: =D8 -> 2.35 | D8: 2.35 | E8: =D8 -> 2.35 | F8: USD/GPU-hr | G8: SemiAnalysis H100 1-yr rental index, Mar 2026. Year-1 rent = the H100 1-year contract index: what a buyer of capacity actually signs.
A9: Years locked by contract | B9: =INDEX(C9:E9,$C$4) -> 1 | C9: 3 | D9: 1 | E9: =D9 -> 1 | F9: years | G9: Base case signs 1-year contracts and re-prices at market each year.
A10: Rent decline per year | B10: =INDEX(C10:E10,$C$4) -> 0.24 | C10: =MAX(0.05,D10-0.08) -> 0.16 | D10: =MIN(0.4,MAX(0.08,ROUND(Ladder!$B$15,2))) -> 0.24 | E10: =MIN(0.45,D10+0.08) -> 0.32 | F10: % per yr | G10: Linked from the Ladder sheet: fitted rate rounded to 2 decimals, bounded 8–40%, the same rule the harness applies.
A11: Utilization | B11: =INDEX(C11:E11,$C$4) -> 0.85 | C11: =MIN(0.95,D11+0.05) -> 0.9 | D11: 0.85 | E11: =MAX(0.4,D11-0.15) -> 0.7 | F11: % of hours | G11: No open data on fleet utilization; 85% leaves room for maintenance and gaps between contracts.
A12: Power per GPU incl. cooling | B12: =INDEX(C12:E12,$C$4) -> 1.4 | C12: =D12 -> 1.4 | D12: 1.4 | E12: =D12 -> 1.4 | F12: kW | G12: Analyst input: 700W GPU + server share, PUE ~1.3.
A13: Electricity | B13: =INDEX(C13:E13,$C$4) -> 0.087 | C13: =D13 -> 0.087 | D13: 0.087 | E13: =D13 -> 0.087 | F13: USD/kWh | G13: EIA Monthly Energy Review Table 9.8, US industrial, May 2026.
A14: Other opex | B14: =INDEX(C14:E14,$C$4) -> 0.3 | C14: =D14 -> 0.3 | D14: 0.3 | E14: =D14 -> 0.3 | F14: USD per available GPU-hr | G14: Analyst input: colocation, network, staff, maintenance.
A15: Economic life | B15: =INDEX(C15:E15,$C$4) -> 5 | C15: 6 | D15: 5 | E15: 4 | F15: years | G15: Between the 2–3 years critics argue and the 6 years used in accounts.
A16: Resale value | B16: =INDEX(C16:E16,$C$4) -> 0.05 | C16: =D16 -> 0.05 | D16: 0.05 | E16: =D16 -> 0.05 | F16: % of capex | G16: Analyst input.
A17: Cost of capital | B17: =INDEX(C17:E17,$C$4) -> 0.11 | C17: =D17 -> 0.11 | D17: 0.11 | E17: =D17 -> 0.11 | F17: % | G17: Equity-heavy financing for a new operator.
A18: Tax rate | B18: =INDEX(C18:E18,$C$4) -> 0.21 | C18: =D18 -> 0.21 | D18: 0.21 | E18: =D18 -> 0.21 | F18: % | G18: US federal corporate rate; losses assumed usable by the wider business.
A19: Hours per year | B19: =INDEX(C19:E19,$C$4) -> 8760 | C19: =D19 -> 8760 | D19: 8760 | E19: =D19 -> 8760 | F19: hours

Sheet Model
A1: Cash flows per GPU (USD)
A2: Rent holds at the year-1 rate while locked by contract, then follows the market curve: rent × (1 − decline)^(year − 1). Columns past the life show zero.
A4: Year | B4: 0 | C4: 1 | D4: 2 | E4: 3 | F4: 4 | G4: 5 | H4: 6 | I4: 7 | J4: 8
A5: Active (1 = in life) | C5: =IF(1<=Inputs!$B$15,1,0) -> 1 | D5: =IF(2<=Inputs!$B$15,1,0) -> 1 | E5: =IF(3<=Inputs!$B$15,1,0) -> 1 | F5: =IF(4<=Inputs!$B$15,1,0) -> 1 | G5: =IF(5<=Inputs!$B$15,1,0) -> 1 | H5: =IF(6<=Inputs!$B$15,1,0) -> 0 | I5: =IF(7<=Inputs!$B$15,1,0) -> 0 | J5: =IF(8<=Inputs!$B$15,1,0) -> 0
A6: Rent ($/hr) | C6: =IF(1<=Inputs!$B$9,Inputs!$B$8,Inputs!$B$8*(1-Inputs!$B$10)^(1-1))*C5 -> 2.35 | D6: =IF(2<=Inputs!$B$9,Inputs!$B$8,Inputs!$B$8*(1-Inputs!$B$10)^(2-1))*D5 -> 1.786 | E6: =IF(3<=Inputs!$B$9,Inputs!$B$8,Inputs!$B$8*(1-Inputs!$B$10)^(3-1))*E5 -> 1.35736 | F6: =IF(4<=Inputs!$B$9,Inputs!$B$8,Inputs!$B$8*(1-Inputs!$B$10)^(4-1))*F5 -> 1.0315936 | G6: =IF(5<=Inputs!$B$9,Inputs!$B$8,Inputs!$B$8*(1-Inputs!$B$10)^(5-1))*G5 -> 0.78401114 | H6: =IF(6<=Inputs!$B$9,Inputs!$B$8,Inputs!$B$8*(1-Inputs!$B$10)^(6-1))*H5 -> 0 | I6: =IF(7<=Inputs!$B$9,Inputs!$B$8,Inputs!$B$8*(1-Inputs!$B$10)^(7-1))*I5 -> 0 | J6: =IF(8<=Inputs!$B$9,Inputs!$B$8,Inputs!$B$8*(1-Inputs!$B$10)^(8-1))*J5 -> 0
A7: Revenue | C7: =C6*Inputs!$B$19*Inputs!$B$11 -> 17498.1 | D7: =D6*Inputs!$B$19*Inputs!$B$11 -> 13298.556 | E7: =E6*Inputs!$B$19*Inputs!$B$11 -> 10106.903 | F7: =F6*Inputs!$B$19*Inputs!$B$11 -> 7681.2459 | G7: =G6*Inputs!$B$19*Inputs!$B$11 -> 5837.7469 | H7: =H6*Inputs!$B$19*Inputs!$B$11 -> 0 | I7: =I6*Inputs!$B$19*Inputs!$B$11 -> 0 | J7: =J6*Inputs!$B$19*Inputs!$B$11 -> 0
A8: Power | C8: =-Inputs!$B$12*Inputs!$B$19*Inputs!$B$11*Inputs!$B$13*C5 -> -906.9228 | D8: =-Inputs!$B$12*Inputs!$B$19*Inputs!$B$11*Inputs!$B$13*D5 -> -906.9228 | E8: =-Inputs!$B$12*Inputs!$B$19*Inputs!$B$11*Inputs!$B$13*E5 -> -906.9228 | F8: =-Inputs!$B$12*Inputs!$B$19*Inputs!$B$11*Inputs!$B$13*F5 -> -906.9228 | G8: =-Inputs!$B$12*Inputs!$B$19*Inputs!$B$11*Inputs!$B$13*G5 -> -906.9228 | H8: =-Inputs!$B$12*Inputs!$B$19*Inputs!$B$11*Inputs!$B$13*H5 -> 0 | I8: =-Inputs!$B$12*Inputs!$B$19*Inputs!$B$11*Inputs!$B$13*I5 -> 0 | J8: =-Inputs!$B$12*Inputs!$B$19*Inputs!$B$11*Inputs!$B$13*J5 -> 0
A9: Other opex | C9: =-Inputs!$B$14*Inputs!$B$19*C5 -> -2628 | D9: =-Inputs!$B$14*Inputs!$B$19*D5 -> -2628 | E9: =-Inputs!$B$14*Inputs!$B$19*E5 -> -2628 | F9: =-Inputs!$B$14*Inputs!$B$19*F5 -> -2628 | G9: =-Inputs!$B$14*Inputs!$B$19*G5 -> -2628 | H9: =-Inputs!$B$14*Inputs!$B$19*H5 -> 0 | I9: =-Inputs!$B$14*Inputs!$B$19*I5 -> 0 | J9: =-Inputs!$B$14*Inputs!$B$19*J5 -> 0
A10: EBITDA | C10: =C7+C8+C9 -> 13963.177 | D10: =D7+D8+D9 -> 9763.6332 | E10: =E7+E8+E9 -> 6571.9798 | F10: =F7+F8+F9 -> 4146.3231 | G10: =G7+G8+G9 -> 2302.8241 | H10: =H7+H8+H9 -> 0 | I10: =I7+I8+I9 -> 0 | J10: =J7+J8+J9 -> 0
A11: Depreciation | C11: =-Inputs!$B$7/Inputs!$B$15*C5 -> -7000 | D11: =-Inputs!$B$7/Inputs!$B$15*D5 -> -7000 | E11: =-Inputs!$B$7/Inputs!$B$15*E5 -> -7000 | F11: =-Inputs!$B$7/Inputs!$B$15*F5 -> -7000 | G11: =-Inputs!$B$7/Inputs!$B$15*G5 -> -7000 | H11: =-Inputs!$B$7/Inputs!$B$15*H5 -> 0 | I11: =-Inputs!$B$7/Inputs!$B$15*I5 -> 0 | J11: =-Inputs!$B$7/Inputs!$B$15*J5 -> 0
A12: EBIT | C12: =C10+C11 -> 6963.1772 | D12: =D10+D11 -> 2763.6332 | E12: =E10+E11 -> -428.02024 | F12: =F10+F11 -> -2853.6769 | G12: =G10+G11 -> -4697.1759 | H12: =H10+H11 -> 0 | I12: =I10+I11 -> 0 | J12: =J10+J11 -> 0
A13: Tax (negative = shield) | C13: =-C12*Inputs!$B$18 -> -1462.2672 | D13: =-D12*Inputs!$B$18 -> -580.36297 | E13: =-E12*Inputs!$B$18 -> 89.88425 | F13: =-F12*Inputs!$B$18 -> 599.27214 | G13: =-G12*Inputs!$B$18 -> 986.40694 | H13: =-H12*Inputs!$B$18 -> 0 | I13: =-I12*Inputs!$B$18 -> 0 | J13: =-J12*Inputs!$B$18 -> 0
A14: Resale value | C14: =IF(1=Inputs!$B$15,Inputs!$B$16*Inputs!$B$7,0) -> 0 | D14: =IF(2=Inputs!$B$15,Inputs!$B$16*Inputs!$B$7,0) -> 0 | E14: =IF(3=Inputs!$B$15,Inputs!$B$16*Inputs!$B$7,0) -> 0 | F14: =IF(4=Inputs!$B$15,Inputs!$B$16*Inputs!$B$7,0) -> 0 | G14: =IF(5=Inputs!$B$15,Inputs!$B$16*Inputs!$B$7,0) -> 1750 | H14: =IF(6=Inputs!$B$15,Inputs!$B$16*Inputs!$B$7,0) -> 0 | I14: =IF(7=Inputs!$B$15,Inputs!$B$16*Inputs!$B$7,0) -> 0 | J14: =IF(8=Inputs!$B$15,Inputs!$B$16*Inputs!$B$7,0) -> 0
A15: Free cash flow | B15: =-Inputs!$B$7 -> -35000 | C15: =C10+C13+C14 -> 12500.91 | D15: =D10+D13+D14 -> 9183.2702 | E15: =E10+E13+E14 -> 6661.864 | F15: =F10+F13+F14 -> 4745.5953 | G15: =G10+G13+G14 -> 5039.2311 | H15: =H10+H13+H14 -> 0 | I15: =I10+I13+I14 -> 0 | J15: =J10+J13+J14 -> 0
A16: Cumulative FCF | B16: =B15 -> -35000 | C16: =B16+C15 -> -22499.09 | D16: =C16+D15 -> -13315.82 | E16: =D16+E15 -> -6653.9558 | F16: =E16+F15 -> -1908.3605 | G16: =F16+G15 -> 3130.8706 | H16: =G16+H15 -> 3130.8706 | I16: =H16+I15 -> 3130.8706 | J16: =I16+J15 -> 3130.8706
A17: Rent coefficient (PV per $1 of rent) | C17: =IF(Inputs!$B$8>0,C6/Inputs!$B$8,0)*Inputs!$B$19*Inputs!$B$11*(1-Inputs!$B$18)/(1+Inputs!$B$17)^1 -> 5299.4054 | D17: =IF(Inputs!$B$8>0,D6/Inputs!$B$8,0)*Inputs!$B$19*Inputs!$B$11*(1-Inputs!$B$18)/(1+Inputs!$B$17)^2 -> 3628.4217 | E17: =IF(Inputs!$B$8>0,E6/Inputs!$B$8,0)*Inputs!$B$19*Inputs!$B$11*(1-Inputs!$B$18)/(1+Inputs!$B$17)^3 -> 2484.3248 | F17: =IF(Inputs!$B$8>0,F6/Inputs!$B$8,0)*Inputs!$B$19*Inputs!$B$11*(1-Inputs!$B$18)/(1+Inputs!$B$17)^4 -> 1700.9791 | G17: =IF(Inputs!$B$8>0,G6/Inputs!$B$8,0)*Inputs!$B$19*Inputs!$B$11*(1-Inputs!$B$18)/(1+Inputs!$B$17)^5 -> 1164.6344 | H17: =IF(Inputs!$B$8>0,H6/Inputs!$B$8,0)*Inputs!$B$19*Inputs!$B$11*(1-Inputs!$B$18)/(1+Inputs!$B$17)^6 -> 0 | I17: =IF(Inputs!$B$8>0,I6/Inputs!$B$8,0)*Inputs!$B$19*Inputs!$B$11*(1-Inputs!$B$18)/(1+Inputs!$B$17)^7 -> 0 | J17: =IF(Inputs!$B$8>0,J6/Inputs!$B$8,0)*Inputs!$B$19*Inputs!$B$11*(1-Inputs!$B$18)/(1+Inputs!$B$17)^8 -> 0
A18: Capex coefficient (PV per $1 of capex) | B18: -1 | C18: =(C5*Inputs!$B$18/Inputs!$B$15+IF(1=Inputs!$B$15,Inputs!$B$16,0))/(1+Inputs!$B$17)^1 -> 0.037837838 | D18: =(D5*Inputs!$B$18/Inputs!$B$15+IF(2=Inputs!$B$15,Inputs!$B$16,0))/(1+Inputs!$B$17)^2 -> 0.034088142 | E18: =(E5*Inputs!$B$18/Inputs!$B$15+IF(3=Inputs!$B$15,Inputs!$B$16,0))/(1+Inputs!$B$17)^3 -> 0.030710038 | F18: =(F5*Inputs!$B$18/Inputs!$B$15+IF(4=Inputs!$B$15,Inputs!$B$16,0))/(1+Inputs!$B$17)^4 -> 0.027666701 | G18: =(G5*Inputs!$B$18/Inputs!$B$15+IF(5=Inputs!$B$15,Inputs!$B$16,0))/(1+Inputs!$B$17)^5 -> 0.054597522 | H18: =(H5*Inputs!$B$18/Inputs!$B$15+IF(6=Inputs!$B$15,Inputs!$B$16,0))/(1+Inputs!$B$17)^6 -> 0 | I18: =(I5*Inputs!$B$18/Inputs!$B$15+IF(7=Inputs!$B$15,Inputs!$B$16,0))/(1+Inputs!$B$17)^7 -> 0 | J18: =(J5*Inputs!$B$18/Inputs!$B$15+IF(8=Inputs!$B$15,Inputs!$B$16,0))/(1+Inputs!$B$17)^8 -> 0
A21: Results
A22: NPV per GPU | B22: =B15+NPV(Inputs!$B$17,C15:J15) -> -5296.8643
A23: NPV, 1,000-GPU cluster | B23: =B22*1000 -> -5296864.3
A24: IRR | B24: =IFERROR(IRR(B15:J15),"n/a") -> 0.035461695
A25: Payback (years) | B25: =IFERROR(MATCH(TRUE(),INDEX(C16:J16>=0,0),0)-1+(-INDEX(B16:I16,MATCH(TRUE(),INDEX(C16:J16>=0,0),0))/INDEX(C15:J15,MATCH(TRUE(),INDEX(C16:J16>=0,0),0))),"Not within life") -> 4.3787007
A26: Break-even year-1 rent ($/hr) | B26: =Inputs!$B$8-B22/SUM(C17:J17) -> 2.7209869 | C26: NPV is linear in rent and in capex, so the break-evens are exact: current value minus NPV ÷ PV coefficient.
A27: Max capex per GPU to break even | B27: =Inputs!$B$7-B22/SUM(B18:J18) -> 28501.575
A28: Cash cost per billed GPU-hour | B28: =Inputs!$B$12*Inputs!$B$13+Inputs!$B$14/Inputs!$B$11 -> 0.47474118
A29: Year-1 EBIT margin, economic life | B29: =IFERROR(C12/C7,0) -> 0.39793904
A30: Year-1 EBIT margin, 6-year accounting life | B30: =IFERROR((C10-Inputs!$B$7/6)/C7,0) -> 0.46461295

Sheet Ladder
A1: Price ladder: rent vs years on the market (evidence for the rent-decline assumption)
A2: Source: GetDeploying GPU price dataset (CC BY 4.0), on-demand median, average of the last 4 complete weeks to 2026-09-28. Availability year = analyst input.
A4: As-of year (decimal) | B4: 2026.67
A6: GPU | B6: Volume availability (year) | C6: Years on market | D6: Rent $/GPU-hr | E6: LN(rent) | F6: 12-month change
A7: A100 | B7: 2020.4 | C7: =$B$4-B7 -> 6.27 | D7: 1.74 | E7: =LN(D7) -> 0.55388511 | F7: 0.041
A8: H100 | B8: 2022.9 | C8: =$B$4-B8 -> 3.77 | D8: 3.36 | E8: =LN(D8) -> 1.211941 | F8: 0.126
A9: H200 | B9: 2024.3 | C9: =$B$4-B9 -> 2.37 | D9: 4.45 | E9: =LN(D9) -> 1.4929041 | F9: 0.27
A10: B200 | B10: 2025.1 | C10: =$B$4-B10 -> 1.57 | D10: 6.51 | E10: =LN(D10) -> 1.8733395 | F10: 0.142
A11: B300 | B11: 2025.8 | C11: =$B$4-B11 -> 0.87 | D11: 8.07 | E11: =LN(D11) -> 2.0881535 | F11: 0.545
A13: Slope of LN(rent) per year | B13: =SLOPE(E7:E11,C7:C11) -> -0.27963671
A14: R² | B14: =RSQ(E7:E11,C7:C11) -> 0.98622612
A15: Rent lost per year of age | B15: =1-EXP(B13) -> 0.24394164

Sheet H100 weekly
A1: H100 on-demand median rent, USD/GPU-hr (GetDeploying, CC BY 4.0)
A3: Week | B3: Median rent
A4: 2025-10-06 | B4: 2.985
A5: 2025-10-13 | B5: 2.985
A6: 2025-10-20 | B6: 2.985
A7: 2025-10-27 | B7: 2.985
A8: 2025-11-03 | B8: 2.985
A9: 2025-11-10 | B9: 2.99
A10: 2025-11-17 | B10: 2.985
A11: 2025-11-24 | B11: 2.99
A12: 2025-12-01 | B12: 2.99
A13: 2025-12-08 | B13: 2.99
A14: 2025-12-15 | B14: 2.99
A15: 2025-12-22 | B15: 2.99
... A55: 2026-09-28 | B55: 3.382

Sheet Sources
A1: Sources
A3: GetDeploying GPU price dataset (CC BY 4.0) | B3: https://getdeploying.com/dataset/gpu-prices
A4: SemiAnalysis H100 1-yr rental index | B4: https://newsletter.semianalysis.com/p/the-great-gpu-shortage-rental-capacity
A5: EIA Monthly Energy Review, electricity prices | B5: https://www.eia.gov/TOTALENERGY/data/monthly/pdf/sec9_10.pdf
A6: CoreWeave Form 10-K FY2025 | B6: https://www.sec.gov/Archives/edgar/data/1769628/000176962826000104/crwv-20251231.htm
A7: Research harness code and run log | B7: https://github.com/P3K30NG0T/tomphan
A10: Data as of 2026-09-28. Independent analysis on open data by Phan Nguyen Hong Quang (tomphan.). Not investment advice.
